{
    "users": [{
            "aboutMe": "Не знаю что написать про себя...",
            "Name": "Nikita",
            "password": "3275",
            "gmail": "nikita@taki.pro",
            "department": null,
            "branch": null,
            "deliveryDate": "2020-12-17",
            "adress": "Москва ",
            "isAdmin": false,
            "cookie": "6^zw^61r8jov",
            "Position": "Hz"
        },
        {
            "aboutMe": "Не знаю что написать про себя...",
            "Name": "Nikita",
            "password": "3275",
            "gmail": "nikita@taki.pro",
            "department": null,
            "branch": null,
            "deliveryDate": "2020-12-17",
            "adress": "Москва ",
            "isAdmin": false,
            "cookie": "6^zw^61r8jov",
            "Position": "Hz"
        },
        {
            "aboutMe": "Не знаю что написать про себя...",
            "Name": "Nikita",
            "password": "3275",
            "gmail": "nikita@taki.pro",
            "department": null,
            "branch": null,
            "deliveryDate": "2020-12-17",
            "adress": "Москва ",
            "isAdmin": false,
            "cookie": "6^zw^61r8jov",
            "Position": "Hz"
        },
        {
            "aboutMe": "Не знаю что написать про себя...",
            "Name": "Nikita",
            "password": "3275",
            "gmail": "nikita@taki.pro",
            "department": null,
            "branch": null,
            "deliveryDate": "2020-12-17",
            "adress": "Москва ",
            "isAdmin": false,
            "cookie": "6^zw^61r8jov",
            "Position": "Hz"
        },
        {
            "aboutMe": "Не знаю что написать про себя...",
            "Name": "Nikita",
            "password": "3275",
            "gmail": "nikita@taki.pro",
            "department": null,
            "branch": null,
            "deliveryDate": "2020-12-17",
            "adress": "Москва ",
            "isAdmin": false,
            "cookie": "6^zw^61r8jov",
            "Position": "Hz"
        },
        {
            "aboutMe": "Не знаю что написать про себя...",
            "Name": "Nikita",
            "password": "3275",
            "gmail": "nikita@taki.pro",
            "department": null,
            "branch": null,
            "deliveryDate": "2020-12-17",
            "adress": "Москва ",
            "isAdmin": false,
            "cookie": "6^zw^61r8jov",
            "Position": "Hz"
        }
    ]
}